import com.twitter.platform.PlatformContext;
import com.twitter.platform.o;
import com.twitter.util.collection.n;
import com.twitter.util.j;
import java.io.ByteArrayOutputStream;
import java.io.Closeable;
import java.io.File;
import java.io.IOException;
import java.io.InputStream;
import java.io.ObjectInput;
import java.io.OutputStream;
import java.nio.charset.Charset;

public class cxr
{
  public static int a(InputStream paramInputStream)
  {
    
    try
    {
      int i = a(paramInputStream, null, 4096);
      return i;
    }
    catch (IOException paramInputStream) {}
    return 0;
  }
  
  public static int a(InputStream paramInputStream, OutputStream paramOutputStream, int paramInt)
    throws IOException
  {
    j.c();
    byte[] arrayOfByte = new byte[paramInt];
    paramInt = 0;
    for (;;)
    {
      int i = paramInputStream.read(arrayOfByte);
      if (i == -1) {
        break;
      }
      if (paramOutputStream != null) {
        paramOutputStream.write(arrayOfByte, 0, i);
      }
      paramInt += i;
    }
    return paramInt;
  }
  
  public static File a(InputStream paramInputStream, String paramString)
  {
    j.c();
    paramString = PlatformContext.e().d().a(paramString);
    if (paramString == null) {
      return null;
    }
    if (a(paramInputStream, paramString)) {}
    for (paramInputStream = paramString;; paramInputStream = null) {
      return paramInputStream;
    }
  }
  
  public static Iterable<File> a(File paramFile, boolean paramBoolean)
  {
    String[] arrayOfString = paramFile.list();
    if (arrayOfString == null) {
      return n.g();
    }
    if (paramBoolean) {
      return new cxs(paramFile, arrayOfString);
    }
    return cws.b(cws.a(arrayOfString), new cxu(paramFile));
  }
  
  public static String a(String paramString)
  {
    if (paramString == null) {}
    int i;
    do
    {
      return null;
      i = paramString.lastIndexOf('.');
    } while ((i <= 0) || (i >= paramString.length() - 1));
    return paramString.substring(i + 1).toLowerCase();
  }
  
  /* Error */
  public static java.util.List<String> a(File paramFile, Charset paramCharset)
  {
    // Byte code:
    //   0: invokestatic 14	com/twitter/util/j:c	()V
    //   3: new 107	java/io/FileInputStream
    //   6: dup
    //   7: aload_0
    //   8: invokespecial 108	java/io/FileInputStream:<init>	(Ljava/io/File;)V
    //   11: astore_2
    //   12: aload_2
    //   13: astore_0
    //   14: new 110	java/io/BufferedReader
    //   17: dup
    //   18: new 112	java/io/InputStreamReader
    //   21: dup
    //   22: aload_2
    //   23: aload_1
    //   24: invokespecial 115	java/io/InputStreamReader:<init>	(Ljava/io/InputStream;Ljava/nio/charset/Charset;)V
    //   27: invokespecial 118	java/io/BufferedReader:<init>	(Ljava/io/Reader;)V
    //   30: astore_1
    //   31: aload_2
    //   32: astore_0
    //   33: new 120	java/util/ArrayList
    //   36: dup
    //   37: invokespecial 122	java/util/ArrayList:<init>	()V
    //   40: astore_3
    //   41: aload_2
    //   42: astore_0
    //   43: aload_1
    //   44: invokevirtual 125	java/io/BufferedReader:readLine	()Ljava/lang/String;
    //   47: astore 4
    //   49: aload 4
    //   51: ifnonnull +9 -> 60
    //   54: aload_2
    //   55: invokestatic 128	cxr:a	(Ljava/io/Closeable;)V
    //   58: aload_3
    //   59: areturn
    //   60: aload_2
    //   61: astore_0
    //   62: aload_3
    //   63: aload 4
    //   65: invokeinterface 134 2 0
    //   70: pop
    //   71: goto -30 -> 41
    //   74: astore_0
    //   75: aload_2
    //   76: astore_1
    //   77: aload_0
    //   78: astore_2
    //   79: aload_1
    //   80: astore_0
    //   81: aload_2
    //   82: invokestatic 139	beq:a	(Ljava/lang/Throwable;)V
    //   85: aload_1
    //   86: astore_0
    //   87: invokestatic 63	com/twitter/util/collection/n:g	()Ljava/util/List;
    //   90: astore_2
    //   91: aload_1
    //   92: invokestatic 128	cxr:a	(Ljava/io/Closeable;)V
    //   95: aload_2
    //   96: areturn
    //   97: astore_1
    //   98: aconst_null
    //   99: astore_0
    //   100: aload_0
    //   101: invokestatic 128	cxr:a	(Ljava/io/Closeable;)V
    //   104: aload_1
    //   105: athrow
    //   106: astore_1
    //   107: goto -7 -> 100
    //   110: astore_2
    //   111: aconst_null
    //   112: astore_1
    //   113: goto -34 -> 79
    // Local variable table:
    //   start	length	slot	name	signature
    //   0	116	0	paramFile	File
    //   0	116	1	paramCharset	Charset
    //   11	85	2	localObject	Object
    //   110	1	2	localIOException	IOException
    //   40	23	3	localArrayList	java.util.ArrayList
    //   47	17	4	str	String
    // Exception table:
    //   from	to	target	type
    //   14	31	74	java/io/IOException
    //   33	41	74	java/io/IOException
    //   43	49	74	java/io/IOException
    //   62	71	74	java/io/IOException
    //   3	12	97	finally
    //   14	31	106	finally
    //   33	41	106	finally
    //   43	49	106	finally
    //   62	71	106	finally
    //   81	85	106	finally
    //   87	91	106	finally
    //   3	12	110	java/io/IOException
  }
  
  public static void a(Closeable paramCloseable)
  {
    if (paramCloseable != null) {}
    try
    {
      paramCloseable.close();
      return;
    }
    catch (IOException paramCloseable) {}
  }
  
  public static void a(File paramFile)
    throws IOException
  {
    
    if ((paramFile.exists()) && (!paramFile.isDirectory())) {
      throw new IllegalArgumentException("not a directory: " + paramFile);
    }
    File[] arrayOfFile = paramFile.listFiles();
    if (arrayOfFile != null)
    {
      int j = arrayOfFile.length;
      int i = 0;
      if (i < j)
      {
        File localFile = arrayOfFile[i];
        if (localFile.isDirectory()) {
          a(localFile);
        }
        for (;;)
        {
          i += 1;
          break;
          c(localFile);
        }
      }
    }
    c(paramFile);
  }
  
  public static void a(File paramFile1, File paramFile2)
    throws IOException
  {
    
    if (!paramFile1.renameTo(paramFile2)) {
      throw new IOException("file not renamed " + paramFile1 + " " + paramFile2);
    }
  }
  
  public static void a(byte[] paramArrayOfByte, ObjectInput paramObjectInput)
    throws IOException
  {
    int i = paramArrayOfByte.length;
    int j = 0;
    while (i > 0)
    {
      int k = paramObjectInput.read(paramArrayOfByte, j, i);
      if (k == -1) {
        break;
      }
      j += k;
      i -= k;
    }
  }
  
  /* Error */
  public static boolean a(InputStream paramInputStream, File paramFile)
  {
    // Byte code:
    //   0: iconst_0
    //   1: istore_3
    //   2: iconst_0
    //   3: istore 6
    //   5: iconst_0
    //   6: istore 5
    //   8: iconst_0
    //   9: istore 4
    //   11: iconst_0
    //   12: istore_2
    //   13: invokestatic 14	com/twitter/util/j:c	()V
    //   16: aload_1
    //   17: invokestatic 198	cxr:e	(Ljava/io/File;)Z
    //   20: ifeq +65 -> 85
    //   23: new 200	java/io/FileOutputStream
    //   26: dup
    //   27: aload_1
    //   28: invokespecial 201	java/io/FileOutputStream:<init>	(Ljava/io/File;)V
    //   31: astore 8
    //   33: iload 5
    //   35: istore_3
    //   36: aload 8
    //   38: astore 7
    //   40: aload_0
    //   41: aload 8
    //   43: sipush 4096
    //   46: invokestatic 17	cxr:a	(Ljava/io/InputStream;Ljava/io/OutputStream;I)I
    //   49: ifeq +5 -> 54
    //   52: iconst_1
    //   53: istore_2
    //   54: iload_2
    //   55: istore_3
    //   56: aload 8
    //   58: astore 7
    //   60: iload_2
    //   61: istore 4
    //   63: aload 8
    //   65: invokevirtual 204	java/io/FileOutputStream:flush	()V
    //   68: aload 8
    //   70: invokestatic 128	cxr:a	(Ljava/io/Closeable;)V
    //   73: iload_2
    //   74: istore_3
    //   75: iload_2
    //   76: ifne +9 -> 85
    //   79: aload_1
    //   80: invokestatic 206	cxr:d	(Ljava/io/File;)V
    //   83: iload_2
    //   84: istore_3
    //   85: iload_3
    //   86: ireturn
    //   87: astore 9
    //   89: aconst_null
    //   90: astore_0
    //   91: iload 6
    //   93: istore_2
    //   94: iload_2
    //   95: istore_3
    //   96: aload_0
    //   97: astore 7
    //   99: aload 9
    //   101: invokestatic 139	beq:a	(Ljava/lang/Throwable;)V
    //   104: aload_0
    //   105: invokestatic 128	cxr:a	(Ljava/io/Closeable;)V
    //   108: iload_2
    //   109: istore_3
    //   110: iload_2
    //   111: ifne -26 -> 85
    //   114: aload_1
    //   115: invokestatic 206	cxr:d	(Ljava/io/File;)V
    //   118: iload_2
    //   119: ireturn
    //   120: astore_0
    //   121: aconst_null
    //   122: astore 7
    //   124: iconst_0
    //   125: istore_2
    //   126: aload 7
    //   128: invokestatic 128	cxr:a	(Ljava/io/Closeable;)V
    //   131: iload_2
    //   132: ifne +7 -> 139
    //   135: aload_1
    //   136: invokestatic 206	cxr:d	(Ljava/io/File;)V
    //   139: aload_0
    //   140: athrow
    //   141: astore_0
    //   142: iload_3
    //   143: istore_2
    //   144: goto -18 -> 126
    //   147: astore 9
    //   149: iload 4
    //   151: istore_2
    //   152: aload 8
    //   154: astore_0
    //   155: goto -61 -> 94
    // Local variable table:
    //   start	length	slot	name	signature
    //   0	158	0	paramInputStream	InputStream
    //   0	158	1	paramFile	File
    //   12	140	2	bool1	boolean
    //   1	142	3	bool2	boolean
    //   9	141	4	bool3	boolean
    //   6	28	5	bool4	boolean
    //   3	89	6	bool5	boolean
    //   38	89	7	localObject	Object
    //   31	122	8	localFileOutputStream	java.io.FileOutputStream
    //   87	13	9	localIOException1	IOException
    //   147	1	9	localIOException2	IOException
    // Exception table:
    //   from	to	target	type
    //   23	33	87	java/io/IOException
    //   23	33	120	finally
    //   40	52	141	finally
    //   63	68	141	finally
    //   99	104	141	finally
    //   40	52	147	java/io/IOException
    //   63	68	147	java/io/IOException
  }
  
  public static boolean a(String paramString, File paramFile)
  {
    return a(paramString, Charset.forName("UTF-8"), paramFile);
  }
  
  /* Error */
  public static boolean a(String paramString, Charset paramCharset, File paramFile)
  {
    // Byte code:
    //   0: invokestatic 14	com/twitter/util/j:c	()V
    //   3: aconst_null
    //   4: astore_3
    //   5: new 220	java/io/OutputStreamWriter
    //   8: dup
    //   9: new 200	java/io/FileOutputStream
    //   12: dup
    //   13: aload_2
    //   14: invokespecial 201	java/io/FileOutputStream:<init>	(Ljava/io/File;)V
    //   17: aload_1
    //   18: invokespecial 223	java/io/OutputStreamWriter:<init>	(Ljava/io/OutputStream;Ljava/nio/charset/Charset;)V
    //   21: astore_2
    //   22: aload_2
    //   23: astore_1
    //   24: aload_2
    //   25: aload_0
    //   26: invokevirtual 227	java/io/Writer:write	(Ljava/lang/String;)V
    //   29: aload_2
    //   30: invokestatic 128	cxr:a	(Ljava/io/Closeable;)V
    //   33: iconst_1
    //   34: ireturn
    //   35: astore_3
    //   36: aconst_null
    //   37: astore_0
    //   38: aload_0
    //   39: astore_1
    //   40: aload_3
    //   41: invokestatic 139	beq:a	(Ljava/lang/Throwable;)V
    //   44: aload_0
    //   45: invokestatic 128	cxr:a	(Ljava/io/Closeable;)V
    //   48: iconst_0
    //   49: ireturn
    //   50: astore_0
    //   51: aload_3
    //   52: astore_1
    //   53: aload_1
    //   54: invokestatic 128	cxr:a	(Ljava/io/Closeable;)V
    //   57: aload_0
    //   58: athrow
    //   59: astore_0
    //   60: goto -7 -> 53
    //   63: astore_3
    //   64: aload_2
    //   65: astore_0
    //   66: goto -28 -> 38
    // Local variable table:
    //   start	length	slot	name	signature
    //   0	69	0	paramString	String
    //   0	69	1	paramCharset	Charset
    //   0	69	2	paramFile	File
    //   4	1	3	localObject	Object
    //   35	17	3	localIOException1	IOException
    //   63	1	3	localIOException2	IOException
    // Exception table:
    //   from	to	target	type
    //   5	22	35	java/io/IOException
    //   5	22	50	finally
    //   24	29	59	finally
    //   40	44	59	finally
    //   24	29	63	java/io/IOException
  }
  
  /* Error */
  public static boolean a(byte[] paramArrayOfByte, File paramFile)
  {
    // Byte code:
    //   0: iconst_0
    //   1: istore_2
    //   2: aload_1
    //   3: invokestatic 198	cxr:e	(Ljava/io/File;)Z
    //   6: ifeq +40 -> 46
    //   9: new 200	java/io/FileOutputStream
    //   12: dup
    //   13: aload_1
    //   14: invokespecial 201	java/io/FileOutputStream:<init>	(Ljava/io/File;)V
    //   17: astore 4
    //   19: aload 4
    //   21: astore_3
    //   22: aload 4
    //   24: aload_0
    //   25: iconst_0
    //   26: aload_0
    //   27: arraylength
    //   28: invokevirtual 229	java/io/FileOutputStream:write	([BII)V
    //   31: aload 4
    //   33: astore_3
    //   34: aload 4
    //   36: invokevirtual 204	java/io/FileOutputStream:flush	()V
    //   39: iconst_1
    //   40: istore_2
    //   41: aload 4
    //   43: invokestatic 128	cxr:a	(Ljava/io/Closeable;)V
    //   46: iload_2
    //   47: ireturn
    //   48: astore 5
    //   50: aconst_null
    //   51: astore_0
    //   52: aload_0
    //   53: astore_3
    //   54: aload 5
    //   56: invokestatic 139	beq:a	(Ljava/lang/Throwable;)V
    //   59: aload_0
    //   60: astore_3
    //   61: aload_1
    //   62: invokestatic 206	cxr:d	(Ljava/io/File;)V
    //   65: aload_0
    //   66: invokestatic 128	cxr:a	(Ljava/io/Closeable;)V
    //   69: iconst_0
    //   70: ireturn
    //   71: astore_0
    //   72: aconst_null
    //   73: astore_3
    //   74: aload_3
    //   75: invokestatic 128	cxr:a	(Ljava/io/Closeable;)V
    //   78: aload_0
    //   79: athrow
    //   80: astore_0
    //   81: goto -7 -> 74
    //   84: astore 5
    //   86: aload 4
    //   88: astore_0
    //   89: goto -37 -> 52
    // Local variable table:
    //   start	length	slot	name	signature
    //   0	92	0	paramArrayOfByte	byte[]
    //   0	92	1	paramFile	File
    //   1	46	2	bool	boolean
    //   21	54	3	localObject	Object
    //   17	70	4	localFileOutputStream	java.io.FileOutputStream
    //   48	7	5	localIOException1	IOException
    //   84	1	5	localIOException2	IOException
    // Exception table:
    //   from	to	target	type
    //   9	19	48	java/io/IOException
    //   9	19	71	finally
    //   22	31	80	finally
    //   34	39	80	finally
    //   54	59	80	finally
    //   61	65	80	finally
    //   22	31	84	java/io/IOException
    //   34	39	84	java/io/IOException
  }
  
  public static void b(File paramFile)
  {
    
    if ((paramFile != null) && (paramFile.exists()) && (paramFile.isDirectory()))
    {
      File[] arrayOfFile = paramFile.listFiles();
      if (arrayOfFile != null)
      {
        int j = arrayOfFile.length;
        int i = 0;
        if (i < j)
        {
          File localFile = arrayOfFile[i];
          if (localFile.isDirectory()) {
            b(localFile);
          }
          for (;;)
          {
            i += 1;
            break;
            d(localFile);
          }
        }
      }
      d(paramFile);
    }
  }
  
  /* Error */
  public static boolean b(File paramFile1, File paramFile2)
  {
    // Byte code:
    //   0: invokestatic 14	com/twitter/util/j:c	()V
    //   3: new 107	java/io/FileInputStream
    //   6: dup
    //   7: aload_0
    //   8: invokespecial 108	java/io/FileInputStream:<init>	(Ljava/io/File;)V
    //   11: astore_3
    //   12: aload_3
    //   13: astore_0
    //   14: aload_3
    //   15: aload_1
    //   16: invokestatic 50	cxr:a	(Ljava/io/InputStream;Ljava/io/File;)Z
    //   19: istore_2
    //   20: aload_3
    //   21: invokestatic 128	cxr:a	(Ljava/io/Closeable;)V
    //   24: iload_2
    //   25: ireturn
    //   26: astore 4
    //   28: aconst_null
    //   29: astore_1
    //   30: aload_1
    //   31: astore_0
    //   32: aload 4
    //   34: invokestatic 139	beq:a	(Ljava/lang/Throwable;)V
    //   37: aload_1
    //   38: invokestatic 128	cxr:a	(Ljava/io/Closeable;)V
    //   41: iconst_0
    //   42: ireturn
    //   43: astore_1
    //   44: aconst_null
    //   45: astore_0
    //   46: aload_0
    //   47: invokestatic 128	cxr:a	(Ljava/io/Closeable;)V
    //   50: aload_1
    //   51: athrow
    //   52: astore_1
    //   53: goto -7 -> 46
    //   56: astore 4
    //   58: aload_3
    //   59: astore_1
    //   60: goto -30 -> 30
    // Local variable table:
    //   start	length	slot	name	signature
    //   0	63	0	paramFile1	File
    //   0	63	1	paramFile2	File
    //   19	6	2	bool	boolean
    //   11	48	3	localFileInputStream	java.io.FileInputStream
    //   26	7	4	localIOException1	IOException
    //   56	1	4	localIOException2	IOException
    // Exception table:
    //   from	to	target	type
    //   3	12	26	java/io/IOException
    //   3	12	43	finally
    //   14	20	52	finally
    //   32	37	52	finally
    //   14	20	56	java/io/IOException
  }
  
  public static byte[] b(InputStream paramInputStream)
  {
    ByteArrayOutputStream localByteArrayOutputStream = new ByteArrayOutputStream();
    try
    {
      a(paramInputStream, localByteArrayOutputStream, 4096);
      paramInputStream = localByteArrayOutputStream.toByteArray();
      return paramInputStream;
    }
    catch (IOException paramInputStream)
    {
      beq.a(paramInputStream);
    }
    return null;
  }
  
  public static void c(File paramFile)
    throws IOException
  {
    
    if ((paramFile.exists()) && (!paramFile.delete())) {
      throw new IOException("failed to delete file: " + paramFile);
    }
  }
  
  public static boolean c(File paramFile1, File paramFile2)
  {
    j.c();
    return (e(paramFile2)) && ((paramFile1.renameTo(paramFile2)) || ((b(paramFile1, paramFile2)) && (paramFile1.delete())));
  }
  
  public static void d(File paramFile)
  {
    
    if (paramFile != null) {
      paramFile.delete();
    }
  }
  
  public static boolean e(File paramFile)
  {
    j.c();
    paramFile = paramFile.getParentFile();
    return (paramFile == null) || (paramFile.exists()) || (paramFile.mkdirs());
  }
  
  /* Error */
  public static boolean f(File paramFile)
  {
    // Byte code:
    //   0: invokestatic 14	com/twitter/util/j:c	()V
    //   3: aload_0
    //   4: invokevirtual 258	java/io/File:getAbsolutePath	()Ljava/lang/String;
    //   7: astore_1
    //   8: aload_1
    //   9: iconst_0
    //   10: aload_1
    //   11: getstatic 262	java/io/File:separator	Ljava/lang/String;
    //   14: invokevirtual 265	java/lang/String:lastIndexOf	(Ljava/lang/String;)I
    //   17: invokevirtual 268	java/lang/String:substring	(II)Ljava/lang/String;
    //   20: astore_2
    //   21: new 270	java/util/zip/ZipInputStream
    //   24: dup
    //   25: new 272	java/io/BufferedInputStream
    //   28: dup
    //   29: new 107	java/io/FileInputStream
    //   32: dup
    //   33: aload_0
    //   34: invokespecial 108	java/io/FileInputStream:<init>	(Ljava/io/File;)V
    //   37: invokespecial 275	java/io/BufferedInputStream:<init>	(Ljava/io/InputStream;)V
    //   40: invokespecial 276	java/util/zip/ZipInputStream:<init>	(Ljava/io/InputStream;)V
    //   43: astore_1
    //   44: aload_1
    //   45: astore_0
    //   46: aload_1
    //   47: invokevirtual 280	java/util/zip/ZipInputStream:getNextEntry	()Ljava/util/zip/ZipEntry;
    //   50: astore_3
    //   51: aload_3
    //   52: ifnull +120 -> 172
    //   55: aload_1
    //   56: astore_0
    //   57: aload_3
    //   58: invokevirtual 285	java/util/zip/ZipEntry:getName	()Ljava/lang/String;
    //   61: astore 4
    //   63: aload_1
    //   64: astore_0
    //   65: new 53	java/io/File
    //   68: dup
    //   69: new 156	java/lang/StringBuilder
    //   72: dup
    //   73: invokespecial 157	java/lang/StringBuilder:<init>	()V
    //   76: aload_2
    //   77: invokevirtual 163	java/lang/StringBuilder:append	(Ljava/lang/String;)Ljava/lang/StringBuilder;
    //   80: getstatic 262	java/io/File:separator	Ljava/lang/String;
    //   83: invokevirtual 163	java/lang/StringBuilder:append	(Ljava/lang/String;)Ljava/lang/StringBuilder;
    //   86: aload 4
    //   88: invokevirtual 163	java/lang/StringBuilder:append	(Ljava/lang/String;)Ljava/lang/StringBuilder;
    //   91: invokevirtual 169	java/lang/StringBuilder:toString	()Ljava/lang/String;
    //   94: invokespecial 286	java/io/File:<init>	(Ljava/lang/String;)V
    //   97: astore 4
    //   99: aload_1
    //   100: astore_0
    //   101: aload_3
    //   102: invokevirtual 287	java/util/zip/ZipEntry:isDirectory	()Z
    //   105: ifeq +27 -> 132
    //   108: aload_1
    //   109: astore_0
    //   110: aload 4
    //   112: invokestatic 198	cxr:e	(Ljava/io/File;)Z
    //   115: pop
    //   116: goto -72 -> 44
    //   119: astore_2
    //   120: aload_1
    //   121: astore_0
    //   122: aload_2
    //   123: invokestatic 139	beq:a	(Ljava/lang/Throwable;)V
    //   126: aload_1
    //   127: invokestatic 128	cxr:a	(Ljava/io/Closeable;)V
    //   130: iconst_0
    //   131: ireturn
    //   132: aload_1
    //   133: astore_0
    //   134: aload_1
    //   135: invokestatic 289	cxr:b	(Ljava/io/InputStream;)[B
    //   138: astore_3
    //   139: aload_3
    //   140: ifnull +12 -> 152
    //   143: aload_1
    //   144: astore_0
    //   145: aload_3
    //   146: aload 4
    //   148: invokestatic 291	cxr:a	([BLjava/io/File;)Z
    //   151: pop
    //   152: aload_1
    //   153: astore_0
    //   154: aload_1
    //   155: invokevirtual 294	java/util/zip/ZipInputStream:closeEntry	()V
    //   158: goto -114 -> 44
    //   161: astore_2
    //   162: aload_0
    //   163: astore_1
    //   164: aload_2
    //   165: astore_0
    //   166: aload_1
    //   167: invokestatic 128	cxr:a	(Ljava/io/Closeable;)V
    //   170: aload_0
    //   171: athrow
    //   172: aload_1
    //   173: invokestatic 128	cxr:a	(Ljava/io/Closeable;)V
    //   176: iconst_1
    //   177: ireturn
    //   178: astore_0
    //   179: aconst_null
    //   180: astore_1
    //   181: goto -15 -> 166
    //   184: astore_2
    //   185: aconst_null
    //   186: astore_1
    //   187: goto -67 -> 120
    // Local variable table:
    //   start	length	slot	name	signature
    //   0	190	0	paramFile	File
    //   7	180	1	localObject1	Object
    //   20	57	2	str	String
    //   119	4	2	localIOException1	IOException
    //   161	4	2	localObject2	Object
    //   184	1	2	localIOException2	IOException
    //   50	96	3	localObject3	Object
    //   61	86	4	localObject4	Object
    // Exception table:
    //   from	to	target	type
    //   46	51	119	java/io/IOException
    //   57	63	119	java/io/IOException
    //   65	99	119	java/io/IOException
    //   101	108	119	java/io/IOException
    //   110	116	119	java/io/IOException
    //   134	139	119	java/io/IOException
    //   145	152	119	java/io/IOException
    //   154	158	119	java/io/IOException
    //   46	51	161	finally
    //   57	63	161	finally
    //   65	99	161	finally
    //   101	108	161	finally
    //   110	116	161	finally
    //   122	126	161	finally
    //   134	139	161	finally
    //   145	152	161	finally
    //   154	158	161	finally
    //   3	44	178	finally
    //   3	44	184	java/io/IOException
  }
}

/* Location:
 * Qualified Name:     cxr
 * Java Class Version: 6 (50.0)
 * JD-Core Version:    0.7.1
 */